README.rst
setup.py
two1/__init__.py
two1/cli.py
two1/util.py
two1.egg-info/PKG-INFO
two1.egg-info/SOURCES.txt
two1.egg-info/dependency_links.txt
two1.egg-info/entry_points.txt
two1.egg-info/requires.txt
two1.egg-info/top_level.txt
two1/bitcoin/__init__.py
two1/bitcoin/block.py
two1/bitcoin/coinbase.py
two1/bitcoin/crypto.py
two1/bitcoin/exceptions.py
two1/bitcoin/hash.py
two1/bitcoin/script.py
two1/bitcoin/script_interpreter.py
two1/bitcoin/txn.py
two1/bitcoin/utils.py
two1/bitrequests/__init__.py
two1/bitrequests/bitrequests.py
two1/bitserv/__init__.py
two1/bitserv/models.py
two1/bitserv/payment_methods.py
two1/bitserv/payment_server.py
two1/bitserv/django/__init__.py
two1/bitserv/django/decorator.py
two1/bitserv/django/models.py
two1/bitserv/django/urls.py
two1/bitserv/django/views.py
two1/bitserv/flask/__init__.py
two1/bitserv/flask/decorator.py
two1/blockchain/__init__.py
two1/blockchain/base_provider.py
two1/blockchain/exceptions.py
two1/blockchain/insight_provider.py
two1/blockchain/mock_provider.py
two1/blockchain/twentyone_provider.py
two1/channels/__init__.py
two1/channels/blockchain.py
two1/channels/cli.py
two1/channels/database.py
two1/channels/paymentchannel.py
two1/channels/paymentchannelclient.py
two1/channels/server.py
two1/channels/statemachine.py
two1/channels/walletwrapper.py
two1/commands/__init__.py
two1/commands/buy.py
two1/commands/buybitcoin.py
two1/commands/channels.py
two1/commands/config.py
two1/commands/doctor.py
two1/commands/earn.py
two1/commands/faucet.py
two1/commands/flush.py
two1/commands/help.py
two1/commands/inbox.py
two1/commands/join.py
two1/commands/log.py
two1/commands/login.py
two1/commands/market.py
two1/commands/mine.py
two1/commands/profile.py
two1/commands/publish.py
two1/commands/rate.py
two1/commands/search.py
two1/commands/sell.py
two1/commands/send.py
two1/commands/status.py
two1/commands/uninstall.py
two1/commands/update.py
two1/commands/wallet.py
two1/commands/util/__init__.py
two1/commands/util/account.py
two1/commands/util/bitcoin_computer.py
two1/commands/util/config.py
two1/commands/util/currency.py
two1/commands/util/decorators.py
two1/commands/util/exceptions.py
