Metadata-Version: 1.1
Name: two1
Version: 3.10.0
Summary: Buy and sell anything on the internet with bitcoin.
Home-page: https://21.co
Author: 21
Author-email: support@21.co
License: FreeBSD
Keywords: bitcoin blockchain client server
Platform: UNKNOWN
Classifier: Development Status :: 4 - Beta
Classifier: Intended Audience :: Developers
Classifier: Topic :: Internet
Classifier: License :: OSI Approved :: MIT License
Classifier: Programming Language :: Python :: 3.4
